jadwal/__init__.py
jadwal/jadwal_shalat.py
tests/__init__.py
tests/test_helper.py
tests/test_jadwal_sholat.py
utils/__init__.py
utils/helper.py
jadwal_shalat_kemenag-0.1.1.dist-info/METADATA
jadwal_shalat_kemenag-0.1.1.dist-info/WHEEL
jadwal_shalat_kemenag-0.1.1.dist-info/top_level.txt
jadwal_shalat_kemenag-0.1.1.dist-info/RECORD
