Metadata-Version: 2.1
Name: jadwal-shalat-kemenag
Version: 0.1.1
Summary: Jadwal shalat untuk wilayah Indonesia berdasarkan data dari website https://bimasislam.kemenag.go.id/jadwalshalat
Home-page: https://github.com/thesuhu/jadwal-shalat-kemenag
Author: The Suhu
Author-email: thesuhu@protonmail.com
Requires-Dist: beautifulsoup4
